Metadata-Version: 2.4
Name: iflow-mcp_mcp-server-obsidian-omnisearch
Version: 0.1.1
Summary: MCP server for Obsidian Omnisearch
License-File: LICENSE
Requires-Python: >=3.10
Requires-Dist: httpx>=0.25.0
Requires-Dist: mcp>=1.0.0
Requires-Dist: pydantic>=2.0.0
Requires-Dist: requests>=2.25.0
